bc_sus_columnvalidation/__init__.py
bc_sus_columnvalidation/validation_scripts/__init__.py
bc_sus_columnvalidation/validation_scripts/datatype_check_bool.py
bc_sus_columnvalidation/validation_scripts/datatype_check_date.py
bc_sus_columnvalidation/validation_scripts/datatype_check_integer.py
bc_sus_columnvalidation/validation_scripts/master_data_check.py
bc_sus_columnvalidation/validation_scripts/missing_data_check.py
bc_sus_columnvalidation/validation_scripts/primary_key_check.py
bc_sus_columnvalidation/validation_scripts/value_restriction_check.py
bc_sus_columnvalidation-0.9.2.9.dist-info/METADATA
bc_sus_columnvalidation-0.9.2.9.dist-info/WHEEL
bc_sus_columnvalidation-0.9.2.9.dist-info/top_level.txt
bc_sus_columnvalidation-0.9.2.9.dist-info/RECORD
