Metadata-Version: 2.1
Name: bc-sus-columnvalidation
Version: 0.9.2.9
Summary: UNKNOWN
Home-page: UNKNOWN
License: UNKNOWN
Platform: UNKNOWN
Requires-Dist: pandas
Requires-Dist: openpyxl
